__init__.py
cloudicorn_azurerm.py
cloudicorn_azurerm-0.10.dist-info/METADATA
cloudicorn_azurerm-0.10.dist-info/WHEEL
cloudicorn_azurerm-0.10.dist-info/top_level.txt
cloudicorn_azurerm-0.10.dist-info/RECORD
