Metadata-Version: 2.1
Name: cloudicorn-azurerm
Version: 0.10
Summary: Taking Infrastructure As Code to the next level
Home-page: https://github.com/jumidev/cloudicorn-cli
Author: krezreb
Author-email: josephbeeson@gmail.com
License: MIT
Requires-Dist: azure-identity
Requires-Dist: azure-mgmt-resource
Requires-Dist: azure-mgmt-storage
Requires-Dist: azure-storage-blob
Requires-Dist: cloudicorn-cli
Requires-Dist: msal[broker]
